juscraper/__init__.py
juscraper/tribunal_manager.py
juscraper/aggregators/__init__.py
juscraper/aggregators/datajud/__init__.py
juscraper/aggregators/datajud/client.py
juscraper/aggregators/datajud/download.py
juscraper/aggregators/datajud/mappings.py
juscraper/aggregators/datajud/parse.py
juscraper/aggregators/jusbr/__init__.py
juscraper/aggregators/jusbr/client.py
juscraper/aggregators/jusbr/download.py
juscraper/aggregators/jusbr/parse.py
juscraper/core/base.py
juscraper/core/download.py
juscraper/core/parse_utils.py
juscraper/courts/__init__.py
juscraper/courts/tjdft/__init__.py
juscraper/courts/tjdft/client.py
juscraper/courts/tjdft/download.py
juscraper/courts/tjdft/parse.py
juscraper/courts/tjpr/__init__.py
juscraper/courts/tjpr/client.py
juscraper/courts/tjpr/download.py
juscraper/courts/tjpr/parse.py
juscraper/courts/tjrs/__init__.py
juscraper/courts/tjrs/client.py
juscraper/courts/tjrs/download.py
juscraper/courts/tjrs/parse.py
juscraper/courts/tjsp/__init__.py
juscraper/courts/tjsp/acordao_download.py
juscraper/courts/tjsp/auth.py
juscraper/courts/tjsp/cjpg_download.py
juscraper/courts/tjsp/cjpg_parse.py
juscraper/courts/tjsp/cjsg_download.py
juscraper/courts/tjsp/cjsg_parse.py
juscraper/courts/tjsp/client.py
juscraper/courts/tjsp/cpopg_download.py
juscraper/courts/tjsp/cpopg_parse.py
juscraper/courts/tjsp/cposg_download.py
juscraper/courts/tjsp/cposg_parse.py
juscraper/utils/__init__.py
juscraper/utils/cnj.py
juscraper/utils/logging_cfg.py
juscraper-0.1.5.dist-info/METADATA
juscraper-0.1.5.dist-info/WHEEL
juscraper-0.1.5.dist-info/licenses/LICENSE
juscraper-0.1.5.dist-info/RECORD
