Metadata-Version: 2.4
Name: juscraper
Version: 0.1.5
Summary: Raspador de tribunais e outros sistemas relacionados ao poder judiciário.
Project-URL: Homepage, https://github.com/jtrecenti/juscraper
Project-URL: Documentation, https://jtrecenti.github.io/juscraper/
Project-URL: Repository, https://github.com/jtrecenti/juscraper.git
Project-URL: Bug Tracker, https://github.com/jtrecenti/juscraper/issues
Project-URL: Changelog, https://github.com/jtrecenti/juscraper/blob/main/CHANGELOG.md
Author-email: Julio Trecenti <jtrecenti@gmail.com>
Maintainer-email: Julio Trecenti <jtrecenti@gmail.com>
License: MIT License
License-File: LICENSE
Keywords: brasil,courts,judiciary,legal-data,tribunais,web-scraping
Classifier: Development Status :: 3 - Alpha
Classifier: Intended Audience :: Developers
Classifier: Intended Audience :: Legal Industry
Classifier: License :: OSI Approved :: MIT License
Classifier: Operating System :: OS Independent
Classifier: Programming Language :: Python :: 3
Classifier: Programming Language :: Python :: 3.11
Classifier: Programming Language :: Python :: 3.12
Classifier: Topic :: Internet :: WWW/HTTP :: Browsers
Classifier: Topic :: Software Development :: Libraries :: Python Modules
Classifier: Topic :: Text Processing :: Markup :: HTML
Requires-Python: >=3.11
Requires-Dist: asttokens>=3.0.0
Requires-Dist: beautifulsoup4>=4.13.4
Requires-Dist: browser-cookie3>=0.20.1
Requires-Dist: comm>=0.2.2
Requires-Dist: nest-asyncio>=1.6.0
Requires-Dist: pandas>=2.2.3
Requires-Dist: playwright>=1.46.0
Requires-Dist: pyarrow>=19.0.1
Requires-Dist: pyjwt>=2.10.1
Requires-Dist: pyppeteer>=2.0.0
Requires-Dist: python-dotenv>=1.1.0
Requires-Dist: requests>=2.32.3
Requires-Dist: selenium>=4.31.0
Requires-Dist: tqdm>=4.67.1
Requires-Dist: unidecode>=1.3.8
Requires-Dist: webdriver-manager>=4.0.2
Provides-Extra: dev
Requires-Dist: flake8>=6.0.0; extra == 'dev'
Requires-Dist: isort>=5.12.0; extra == 'dev'
Requires-Dist: mypy>=1.0.0; extra == 'dev'
Requires-Dist: pre-commit>=3.0.0; extra == 'dev'
Requires-Dist: pylint>=3.0.0; extra == 'dev'
Requires-Dist: pytest-asyncio>=0.21.0; extra == 'dev'
Requires-Dist: pytest-cov>=4.0.0; extra == 'dev'
Requires-Dist: pytest>=8.3.5; extra == 'dev'
Provides-Extra: docs
Requires-Dist: ipykernel>=6.29.5; extra == 'docs'
Requires-Dist: ipywidgets>=8.1.7; extra == 'docs'
Requires-Dist: jupyter>=1.0.0; extra == 'docs'
Requires-Dist: quartodoc>=0.11.1; extra == 'docs'
Provides-Extra: web
Requires-Dist: flask>=3.1.1; extra == 'web'
Requires-Dist: joblib>=1.5.0; extra == 'web'
